Metadata-Version: 2.1
Name: dijkstra_for_robots
Version: 1.0.1
Summary: Система навигации робота по глобальной карте.
Home-page: https://github.com/latwiks/dijkstra_for_robots
Author: latwiks
Author-email: latwiks@vk.com
Project-URL: GitHub, https://github.com/latwiks/dijkstra_for_robots
Keywords: dijkstra robot robots дейкстра дейкстры робот алгоритм библиотека путь пути
Classifier: Programming Language :: Python :: 3.12
Classifier: Programming Language :: Python :: 3.11
Classifier: License :: OSI Approved :: MIT License
Classifier: Operating System :: OS Independent
Requires-Python: >=3.11
Requires-Dist: networkx>=3.2.1
Requires-Dist: matplotlib>=3.8.3
